mkdocs_openapi_markdown_plugin/__init__.py
mkdocs_openapi_markdown_plugin/plugin.py
mkdocs_openapi_markdown_plugin-0.2.1.dist-info/METADATA
mkdocs_openapi_markdown_plugin-0.2.1.dist-info/WHEEL
mkdocs_openapi_markdown_plugin-0.2.1.dist-info/entry_points.txt
mkdocs_openapi_markdown_plugin-0.2.1.dist-info/licenses/LICENSE
mkdocs_openapi_markdown_plugin-0.2.1.dist-info/RECORD
