Metadata-Version: 2.3
Name: mkdocs-openapi-markdown-plugin
Version: 0.2.1
Summary: Mkdocs plugin to generate openapi document markdown
Project-URL: Homepage, https://github.com/vrerv/mkdocs-openapi-markdown-plugin
Project-URL: Bug Tracker, https://github.com/vrerv/mkdocs-openapi-markdown-plugin/issues
Author-email: soonoh <soonoh.jung@vrerv.com>
Classifier: Intended Audience :: Developers
Classifier: Intended Audience :: Information Technology
Classifier: Programming Language :: Python
Classifier: Programming Language :: Python :: 3 :: Only
Requires-Python: >=3.7
Requires-Dist: mkdocs==1.4.2
Requires-Dist: openapi-markdown==0.2.1
